adafruit_bmp280.py
adafruit_circuitpython_bmp280-3.3.5.dist-info/LICENSE
adafruit_circuitpython_bmp280-3.3.5.dist-info/METADATA
adafruit_circuitpython_bmp280-3.3.5.dist-info/WHEEL
adafruit_circuitpython_bmp280-3.3.5.dist-info/top_level.txt
adafruit_circuitpython_bmp280-3.3.5.dist-info/RECORD
